LICENSE
README.md
pyproject.toml
setup.py
installation_instruction/__init__.py
installation_instruction/__main__.py
installation_instruction/get_flags_and_options_from_schema.py
installation_instruction/helpers.py
installation_instruction/installation_instruction.py
installation_instruction.egg-info/PKG-INFO
installation_instruction.egg-info/SOURCES.txt
installation_instruction.egg-info/dependency_links.txt
installation_instruction.egg-info/entry_points.txt
installation_instruction.egg-info/requires.txt
installation_instruction.egg-info/top_level.txt
tests/test_get_flags_and_options_from_schema.py
tests/test_helpers.py
tests/test_installation_instruction.py