Metadata-Version: 2.1
Name: installation_instruction
Version: 0.1.1
Summary: Library and CLI for generating installation instructions from json schema and jinja templates.
Maintainer: Kanushka Gupta
Maintainer-email: Adam McKellar <dev@mckellar.eu>, Timo Ege <Timoege@online.de>
License: Apache-2.0
Classifier: Programming Language :: Python :: 3
Classifier: Operating System :: OS Independent
Classifier: License :: OSI Approved :: Apache Software License
Requires-Python: >=3.10
License-File: LICENSE
Requires-Dist: jinja2
Requires-Dist: jsonschema
Requires-Dist: PyYAML
Requires-Dist: click<9.0.0a0
Provides-Extra: tests
Requires-Dist: pytest; extra == "tests"
Requires-Dist: pytest-cov; extra == "tests"
Provides-Extra: docs
Requires-Dist: sphinx; extra == "docs"
Requires-Dist: sphinx_mdinclude; extra == "docs"
Requires-Dist: sphinx_rtd_theme; extra == "docs"
Requires-Dist: sphinx-autoapi; extra == "docs"
